lepus/__init__.py
lepus/connection.py
lepus-0.0.7.dist-info/licenses/LICENSE
lepus-0.0.7.dist-info/METADATA
lepus-0.0.7.dist-info/WHEEL
lepus-0.0.7.dist-info/top_level.txt
lepus-0.0.7.dist-info/RECORD
