Metadata-Version: 2.4
Name: lepus
Version: 0.0.7
Summary: Using RabbitMQ with Python in a simplified way.
Home-page: https://github.com/ElaraDevSolutions/lepus
Author: Marcos Rosa
Author-email: marcos.cantor@gmail.com
License: GNU
Keywords: rabbitmq
Classifier: Development Status :: 5 - Production/Stable
Classifier: Intended Audience :: Developers
Classifier: Topic :: Software Development :: Build Tools
Classifier: License :: OSI Approved :: GNU General Public License (GPL)
Requires-Python: >=3
License-File: LICENSE
Requires-Dist: pika==1.3.2
Dynamic: author
Dynamic: author-email
Dynamic: classifier
Dynamic: description
Dynamic: description-content-type
Dynamic: home-page
Dynamic: keywords
Dynamic: license
Dynamic: license-file
Dynamic: requires-dist
Dynamic: requires-python
Dynamic: summary
